./LICENSE
./PKG-INFO
./README.md
./pyproject.toml
./test_1.vm
./test_2.vm
./texts_filter.py
./texts_formatter.py
./texts_lexer.py
./texts_style.py
vre_language_pygments-0.0.2.dist-info/METADATA
vre_language_pygments-0.0.2.dist-info/WHEEL
vre_language_pygments-0.0.2.dist-info/entry_points.txt
vre_language_pygments-0.0.2.dist-info/licenses/LICENSE
vre_language_pygments-0.0.2.dist-info/RECORD
