Metadata-Version: 2.4
Name: vre-language-pygments
Version: 0.0.2
Summary: Pygments plugin for VRE-Language
Project-URL: Homepage, https://gitlab.kit.edu/kit/virtmat-tools/vre-language-pygments
Project-URL: Download, https://pypi.org/project/vre-language-pygments/#files
Project-URL: Issues, https://gitlab.kit.edu/kit/virtmat-tools/vre-language-pygments/-/issues
Author-email: The Virtmat Tools Team <virtmat-tools@lists.kit.edu>
License-Expression: BSD-3-Clause
License-File: LICENSE
Classifier: Development Status :: 4 - Beta
Classifier: Operating System :: OS Independent
Classifier: Programming Language :: Python :: 3
Classifier: Programming Language :: Python :: 3.10
Classifier: Programming Language :: Python :: 3.11
Classifier: Programming Language :: Python :: 3.12
Requires-Python: >=3.10
Requires-Dist: pygments
